akxvau/__init__.py
akxvau/akxvau.py
akxvau-0.0.69.dist-info/LICENSE
akxvau-0.0.69.dist-info/METADATA
akxvau-0.0.69.dist-info/WHEEL
akxvau-0.0.69.dist-info/entry_points.txt
akxvau-0.0.69.dist-info/top_level.txt
akxvau-0.0.69.dist-info/RECORD
